Metadata-Version: 2.1
Name: dataplex
Version: 0.0.1
Summary: dataplex, a data I/O hub designed for real-time analysis and performance systems
Home-page: https://github.com/ideoforms/dataplex
Author: Daniel Jones
Author-email: dan-code@erase.net
Keywords: data,analysis,statistics,sound,music
Classifier: Topic :: Multimedia :: Sound/Audio
Classifier: Topic :: Artistic Software
Classifier: Topic :: Communications
Classifier: Topic :: Scientific/Engineering :: Information Analysis
Classifier: Topic :: Scientific/Engineering :: Interface Engine/Protocol Translator
Classifier: Development Status :: 3 - Alpha
Classifier: Intended Audience :: Developers
